auto_mechop/__init__.py
auto_mechop/__main__.py
auto_mechop/cli.py
auto_mechop/google_drive.py
auto_mechop/gui.py
auto_mechop/runner.py
auto_mechop/semester.py
auto_mechop/submit.py
auto_mechop/util.py
usc_auto_mechop-1.0.5.dist-info/METADATA
usc_auto_mechop-1.0.5.dist-info/WHEEL
usc_auto_mechop-1.0.5.dist-info/top_level.txt
usc_auto_mechop-1.0.5.dist-info/RECORD
