Metadata-Version: 2.1
Name: usc-auto-mechop
Version: 1.0.5
Summary: Grading distribution package for USC's AME 341
Home-page: UNKNOWN
Author: Michael Leslie
Author-email: michael.128.leslie@gmail.com
License: UNKNOWN
Platform: UNKNOWN
Classifier: Programming Language :: Python :: 3
Classifier: Operating System :: OS Independent
Requires-Python: >=3.6
